gephipy/__init__.py
gephipy/gephipy.py
gephipy/jupyter.py
gephipy/jvm.py
gephipy-0.0.2.dist-info/LICENSE.md
gephipy-0.0.2.dist-info/METADATA
gephipy-0.0.2.dist-info/WHEEL
gephipy-0.0.2.dist-info/RECORD
